{
  "0": {
    "name": "ガオガエン",
    "sex": 1,
    "level": 50,
    "nature": "しんちょう",
    "ability": "もうか",
    "item": "たべのこし",
    "Ttype": "ほのお",
    "moves": [
      "すてゼリフ",
      "ビルドアップ",
      "とんぼがえり",
      "フレアドライブ"
    ],
    "indiv": [
      31,
      31,
      31,
      31,
      31,
      31
    ],
    "effort": [
      152,
      176,
      0,
      0,
      0,
      200
    ]
  },
  "1": {
    "name": "カイリュー",
    "sex": -1,
    "level": 50,
    "nature": "ようき",
    "ability": "マルチスケイル",
    "item": "ひかりのこな",
    "Ttype": "ドラゴン",
    "moves": [
      "ぼうふう",
      "はねやすめ",
      "ドラゴンテール",
      "まもる"
    ],
    "indiv": [
      31,
      31,
      31,
      31,
      31,
      31
    ],
    "effort": [
      252,
      0,
      0,
      0,
      16,
      252
    ]
  },
  "2": {
    "name": "サーフゴー",
    "sex": 1,
    "level": 50,
    "nature": "ひかえめ",
    "ability": "おうごんのからだ",
    "item": "ラムのみ",
    "Ttype": "はがね",
    "moves": [
      "サイコショック",
      "こらえる",
      "10まんボルト",
      "わるだくみ"
    ],
    "indiv": [
      31,
      31,
      31,
      31,
      31,
      31
    ],
    "effort": [
      252,
      0,
      0,
      252,
      0,
      16
    ]
  },
  "3": {
    "name": "ブリガロン",
    "sex": -1,
    "level": 50,
    "nature": "ようき",
    "ability": "しんりょく",
    "item": "オボンのみ",
    "Ttype": "くさ",
    "moves": [
      "ストーンエッジ",
      "じしん",
      "ウッドハンマー",
      "てっぺき"
    ],
    "indiv": [
      31,
      31,
      31,
      31,
      31,
      31
    ],
    "effort": [
      252,
      0,
      0,
      0,
      16,
      252
    ]
  },
  "4": {
    "name": "マスカーニャ",
    "sex": 1,
    "level": 50,
    "nature": "しんちょう",
    "ability": "へんげんじざい",
    "item": "こだわりスカーフ",
    "Ttype": "くさ",
    "moves": [
      "ふいうち",
      "はたきおとす",
      "はどうだん",
      "けたぐり"
    ],
    "indiv": [
      31,
      31,
      31,
      31,
      31,
      31
    ],
    "effort": [
      240,
      0,
      152,
      0,
      136,
      0
    ]
  },
  "5": {
    "name": "ペリッパー",
    "sex": -1,
    "level": 50,
    "nature": "ようき",
    "ability": "あめうけざら",
    "item": "きあいのタスキ",
    "Ttype": "みず",
    "moves": [
      "でんこうせっか",
      "こらえる",
      "ハイドロポンプ",
      "れいとうビーム"
    ],
    "indiv": [
      31,
      31,
      31,
      31,
      31,
      31
    ],
    "effort": [
      252,
      0,
      0,
      0,
      16,
      252
    ]
  }
}