{
  "0": {
    "name": "サザンドラ",
    "sex": 1,
    "level": 50,
    "nature": "ようき",
    "ability": "ふゆう",
    "item": "オボンのみ",
    "Ttype": "あく",
    "moves": [
      "ラスターカノン",
      "だいちのちから",
      "あくのはどう",
      "だいもんじ"
    ],
    "indiv": [
      31,
      31,
      31,
      31,
      31,
      31
    ],
    "effort": [
      92,
      108,
      76,
      88,
      64,
      80
    ]
  },
  "1": {
    "name": "ウルガモス",
    "sex": -1,
    "level": 50,
    "nature": "さみしがり",
    "ability": "ほのおのからだ",
    "item": "かいがらのすず",
    "Ttype": "むし",
    "moves": [
      "こらえる",
      "オーバーヒート",
      "ほのおのまい",
      "ぼうふう"
    ],
    "indiv": [
      31,
      31,
      31,
      31,
      31,
      31
    ],
    "effort": [
      112,
      92,
      96,
      52,
      100,
      56
    ]
  },
  "2": {
    "name": "エンペルト",
    "sex": 1,
    "level": 50,
    "nature": "おくびょう",
    "ability": "かちき",
    "item": "きあいのタスキ",
    "Ttype": "みず",
    "moves": [
      "れいとうビーム",
      "はたきおとす",
      "ハイドロポンプ",
      "くさむすび"
    ],
    "indiv": [
      31,
      31,
      31,
      31,
      31,
      31
    ],
    "effort": [
      72,
      100,
      64,
      76,
      104,
      92
    ]
  },
  "3": {
    "name": "サーフゴー",
    "sex": -1,
    "level": 50,
    "nature": "ずぶとい",
    "ability": "おうごんのからだ",
    "item": "クラボのみ",
    "Ttype": "はがね",
    "moves": [
      "10まんボルト",
      "マジカルシャイン",
      "ラスターカノン",
      "シャドーボール"
    ],
    "indiv": [
      31,
      31,
      31,
      31,
      31,
      31
    ],
    "effort": [
      4,
      0,
      252,
      252,
      0,
      0
    ]
  },
  "4": {
    "name": "アシレーヌ",
    "sex": 1,
    "level": 50,
    "nature": "ようき",
    "ability": "うるおいボイス",
    "item": "オレンのみ",
    "Ttype": "みず",
    "moves": [
      "なみのり",
      "うたかたのアリア",
      "シャドーボール",
      "ねむる"
    ],
    "indiv": [
      31,
      31,
      31,
      31,
      31,
      31
    ],
    "effort": [
      4,
      0,
      252,
      0,
      0,
      252
    ]
  },
  "5": {
    "name": "ドラパルト",
    "sex": -1,
    "level": 50,
    "nature": "ようき",
    "ability": "すりぬけ",
    "item": "ラムのみ",
    "Ttype": "ドラゴン",
    "moves": [
      "げきりん",
      "シャドーボール",
      "りゅうせいぐん",
      "だいもんじ"
    ],
    "indiv": [
      31,
      31,
      31,
      31,
      31,
      31
    ],
    "effort": [
      76,
      64,
      72,
      96,
      92,
      108
    ]
  }
}