{
  "0": {
    "name": "ギャラドス",
    "sex": 1,
    "level": 50,
    "nature": "ようき",
    "ability": "いかく",
    "item": "ギャラドスナイト",
    "Ttype": "みず",
    "moves": [
      "でんじは",
      "ねむる",
      "アイアンヘッド",
      "ちょうはつ"
    ],
    "indiv": [
      31,
      31,
      31,
      31,
      31,
      31
    ],
    "effort": [
      128,
      0,
      136,
      0,
      128,
      136
    ],
    "ev_category": "hybrid"
  },
  "1": {
    "name": "ブリジュラス",
    "sex": -1,
    "level": 50,
    "nature": "れいせい",
    "ability": "じきゅうりょく",
    "item": "こだわりスカーフ",
    "Ttype": "はがね",
    "moves": [
      "じしん",
      "ドラゴンテール",
      "ボディプレス",
      "はどうだん"
    ],
    "indiv": [
      31,
      31,
      31,
      31,
      31,
      31
    ],
    "effort": [
      16,
      252,
      0,
      0,
      0,
      252
    ],
    "ev_category": "max_out"
  },
  "2": {
    "name": "ブリガロン",
    "sex": 1,
    "level": 50,
    "nature": "いじっぱり",
    "ability": "ぼうだん",
    "item": "きあいのハチマキ",
    "Ttype": "くさ",
    "moves": [
      "こうごうせい",
      "ウッドハンマー",
      "ストーンエッジ",
      "ニードルガード"
    ],
    "indiv": [
      31,
      31,
      31,
      31,
      31,
      31
    ],
    "effort": [
      192,
      0,
      168,
      0,
      0,
      168
    ],
    "ev_category": "hybrid"
  },
  "3": {
    "name": "アローラライチュウ",
    "sex": -1,
    "level": 50,
    "nature": "やんちゃ",
    "ability": "サーフテール",
    "item": "きれいなぬけがら",
    "Ttype": "でんき",
    "moves": [
      "サイコショック",
      "10まんボルト",
      "なみのり",
      "わるだくみ"
    ],
    "indiv": [
      31,
      31,
      31,
      31,
      31,
      31
    ],
    "effort": [
      252,
      0,
      0,
      0,
      16,
      252
    ],
    "ev_category": "max_out"
  },
  "4": {
    "name": "コノヨザル",
    "sex": 1,
    "level": 50,
    "nature": "しんちょう",
    "ability": "やるき",
    "item": "たべのこし",
    "Ttype": "かくとう",
    "moves": [
      "こらえる",
      "とんぼがえり",
      "ドレインパンチ",
      "ストーンエッジ"
    ],
    "indiv": [
      31,
      31,
      31,
      31,
      31,
      31
    ],
    "effort": [
      252,
      0,
      16,
      0,
      252,
      0
    ],
    "ev_category": "max_out"
  },
  "5": {
    "name": "サーフゴー",
    "sex": -1,
    "level": 50,
    "nature": "おくびょう",
    "ability": "おうごんのからだ",
    "item": "ラムのみ",
    "Ttype": "はがね",
    "moves": [
      "10まんボルト",
      "こらえる",
      "まもる",
      "ラスターカノン"
    ],
    "indiv": [
      31,
      31,
      31,
      31,
      31,
      31
    ],
    "effort": [
      252,
      0,
      0,
      0,
      16,
      252
    ],
    "ev_category": "max_out"
  }
}