{
  "0": {
    "name": "イダイトウ(オス)",
    "sex": 1,
    "level": 50,
    "nature": "しんちょう",
    "ability": "すいすい",
    "item": "ラムのみ",
    "Ttype": "みず",
    "moves": [
      "れいとうビーム",
      "おはかまいり",
      "こらえる",
      "みがわり"
    ],
    "indiv": [
      31,
      31,
      31,
      31,
      31,
      31
    ],
    "effort": [
      16,
      252,
      0,
      0,
      0,
      252
    ]
  },
  "1": {
    "name": "サザンドラ",
    "sex": -1,
    "level": 50,
    "nature": "おだやか",
    "ability": "ふゆう",
    "item": "たべのこし",
    "Ttype": "あく",
    "moves": [
      "かえんほうしゃ",
      "だいちのちから",
      "りゅうのはどう",
      "あくのはどう"
    ],
    "indiv": [
      31,
      31,
      31,
      31,
      31,
      31
    ],
    "effort": [
      168,
      0,
      216,
      0,
      0,
      144
    ]
  },
  "2": {
    "name": "ドドゲザン",
    "sex": 1,
    "level": 50,
    "nature": "やんちゃ",
    "ability": "プレッシャー",
    "item": "くろいメガネ",
    "Ttype": "あく",
    "moves": [
      "ドゲザン",
      "ハサミギロチン",
      "みがわり",
      "ふいうち"
    ],
    "indiv": [
      31,
      31,
      31,
      31,
      31,
      31
    ],
    "effort": [
      0,
      168,
      0,
      224,
      0,
      136
    ]
  },
  "3": {
    "name": "ドラパルト",
    "sex": -1,
    "level": 50,
    "nature": "やんちゃ",
    "ability": "すりぬけ",
    "item": "きあいのタスキ",
    "Ttype": "ドラゴン",
    "moves": [
      "ドラゴンアロー",
      "だいもんじ",
      "のろい",
      "げきりん"
    ],
    "indiv": [
      31,
      31,
      31,
      31,
      31,
      31
    ],
    "effort": [
      252,
      0,
      16,
      0,
      252,
      0
    ]
  },
  "4": {
    "name": "ウツボット",
    "sex": 1,
    "level": 50,
    "nature": "ようき",
    "ability": "ようりょくそ",
    "item": "ウツボットナイト",
    "Ttype": "くさ",
    "moves": [
      "ふいうち",
      "リーフブレード",
      "ちからをすいとる",
      "こうごうせい"
    ],
    "indiv": [
      31,
      31,
      31,
      31,
      31,
      31
    ],
    "effort": [
      252,
      0,
      0,
      0,
      16,
      252
    ]
  },
  "5": {
    "name": "フシギバナ",
    "sex": -1,
    "level": 50,
    "nature": "ようき",
    "ability": "ようりょくそ",
    "item": "カゴのみ",
    "Ttype": "くさ",
    "moves": [
      "だいちのちから",
      "アシッドボム",
      "やどりぎのタネ",
      "みがわり"
    ],
    "indiv": [
      31,
      31,
      31,
      31,
      31,
      31
    ],
    "effort": [
      168,
      0,
      0,
      184,
      0,
      176
    ]
  }
}