{
  "0": {
    "name": "アーマーガア",
    "sex": 1,
    "level": 50,
    "nature": "しんちょう",
    "ability": "ミラーアーマー",
    "item": "ひかりのこな",
    "Ttype": "ひこう",
    "moves": [
      "つけあがる",
      "ブレイブバード",
      "とんぼがえり",
      "アイアンヘッド"
    ],
    "indiv": [
      31,
      31,
      31,
      31,
      31,
      31
    ],
    "effort": [
      200,
      0,
      184,
      0,
      144,
      0
    ],
    "ev_category": "hybrid"
  },
  "1": {
    "name": "ガブリアス",
    "sex": -1,
    "level": 50,
    "nature": "ゆうかん",
    "ability": "すながくれ",
    "item": "たべのこし",
    "Ttype": "ドラゴン",
    "moves": [
      "だいもんじ",
      "まもる",
      "じしん",
      "げきりん"
    ],
    "indiv": [
      31,
      31,
      31,
      31,
      31,
      31
    ],
    "effort": [
      128,
      0,
      0,
      0,
      184,
      216
    ],
    "ev_category": "hybrid"
  },
  "2": {
    "name": "ヒートロトム",
    "sex": 1,
    "level": 50,
    "nature": "うっかりや",
    "ability": "ふゆう",
    "item": "くろいメガネ",
    "Ttype": "でんき",
    "moves": [
      "ほうでん",
      "イカサマ",
      "いたみわけ",
      "まもる"
    ],
    "indiv": [
      31,
      31,
      31,
      31,
      31,
      31
    ],
    "effort": [
      252,
      252,
      0,
      0,
      0,
      16
    ],
    "ev_category": "max_out"
  },
  "3": {
    "name": "ミロカロス",
    "sex": -1,
    "level": 50,
    "nature": "いじっぱり",
    "ability": "ふしぎなうろこ",
    "item": "ピントレンズ",
    "Ttype": "みず",
    "moves": [
      "じこさいせい",
      "とぐろをまく",
      "ハイドロポンプ",
      "ドラゴンテール"
    ],
    "indiv": [
      31,
      31,
      31,
      31,
      31,
      31
    ],
    "effort": [
      208,
      144,
      176,
      0,
      0,
      0
    ],
    "ev_category": "hybrid"
  },
  "4": {
    "name": "ガオガエン",
    "sex": 1,
    "level": 50,
    "nature": "わんぱく",
    "ability": "もうか",
    "item": "いのちのたま",
    "Ttype": "ほのお",
    "moves": [
      "DDラリアット",
      "まもる",
      "おにび",
      "かわらわり"
    ],
    "indiv": [
      31,
      31,
      31,
      31,
      31,
      31
    ],
    "effort": [
      208,
      0,
      168,
      0,
      0,
      152
    ],
    "ev_category": "hybrid"
  },
  "5": {
    "name": "ゲッコウガ",
    "sex": -1,
    "level": 50,
    "nature": "しんちょう",
    "ability": "へんげんじざい",
    "item": "ゲッコウガナイト",
    "Ttype": "みず",
    "moves": [
      "れいとうビーム",
      "まきびし",
      "ダストシュート",
      "こらえる"
    ],
    "indiv": [
      31,
      31,
      31,
      31,
      31,
      31
    ],
    "effort": [
      168,
      0,
      0,
      0,
      208,
      152
    ],
    "ev_category": "hybrid"
  }
}