{
  "0": {
    "name": "アシレーヌ",
    "sex": 1,
    "level": 50,
    "nature": "わんぱく",
    "ability": "うるおいボイス",
    "item": "チーゴのみ",
    "Ttype": "みず",
    "moves": [
      "ハイパーボイス",
      "エナジーボール",
      "めいそう",
      "クイックターン"
    ],
    "indiv": [
      31,
      31,
      31,
      31,
      31,
      31
    ],
    "effort": [
      100,
      56,
      112,
      76,
      92,
      72
    ]
  },
  "1": {
    "name": "ドラパルト",
    "sex": -1,
    "level": 50,
    "nature": "ずぶとい",
    "ability": "クリアボディ",
    "item": "リリバのみ",
    "Ttype": "ドラゴン",
    "moves": [
      "ふいうち",
      "みがわり",
      "でんじは",
      "シャドーボール"
    ],
    "indiv": [
      31,
      31,
      31,
      31,
      31,
      31
    ],
    "effort": [
      252,
      0,
      0,
      252,
      4,
      0
    ]
  },
  "2": {
    "name": "クチート",
    "sex": 1,
    "level": 50,
    "nature": "ようき",
    "ability": "いかく",
    "item": "カシブのみ",
    "Ttype": "はがね",
    "moves": [
      "みがわり",
      "はたきおとす",
      "ふいうち",
      "いばる"
    ],
    "indiv": [
      31,
      31,
      31,
      31,
      31,
      31
    ],
    "effort": [
      0,
      4,
      252,
      0,
      252,
      0
    ]
  },
  "3": {
    "name": "ドドゲザン",
    "sex": -1,
    "level": 50,
    "nature": "しんちょう",
    "ability": "まけんき",
    "item": "しろいハーブ",
    "Ttype": "あく",
    "moves": [
      "まもる",
      "いわなだれ",
      "ドゲザン",
      "ふいうち"
    ],
    "indiv": [
      31,
      31,
      31,
      31,
      31,
      31
    ],
    "effort": [
      0,
      252,
      252,
      4,
      0,
      0
    ]
  },
  "4": {
    "name": "ラウドボーン",
    "sex": 1,
    "level": 50,
    "nature": "おくびょう",
    "ability": "てんねん",
    "item": "ハバンのみ",
    "Ttype": "ほのお",
    "moves": [
      "シャドーボール",
      "おにび",
      "あくび",
      "フレアソング"
    ],
    "indiv": [
      31,
      31,
      31,
      31,
      31,
      31
    ],
    "effort": [
      4,
      0,
      0,
      252,
      0,
      252
    ]
  },
  "5": {
    "name": "エルフーン",
    "sex": -1,
    "level": 50,
    "nature": "しんちょう",
    "ability": "すりぬけ",
    "item": "シルクのスカーフ",
    "Ttype": "くさ",
    "moves": [
      "おきみやげ",
      "がむしゃら",
      "ちょうはつ",
      "こらえる"
    ],
    "indiv": [
      31,
      31,
      31,
      31,
      31,
      31
    ],
    "effort": [
      0,
      4,
      252,
      252,
      0,
      0
    ]
  }
}