{
  "0": {
    "name": "カイリュー",
    "sex": 1,
    "level": 50,
    "nature": "しんちょう",
    "ability": "マルチスケイル",
    "item": "ものしりメガネ",
    "Ttype": "ドラゴン",
    "moves": [
      "じしん",
      "ほのおのうず",
      "しんそく",
      "ほのおのパンチ"
    ],
    "indiv": [
      31,
      31,
      31,
      31,
      31,
      31
    ],
    "effort": [
      160,
      112,
      160,
      0,
      0,
      96
    ]
  },
  "1": {
    "name": "サーフゴー",
    "sex": -1,
    "level": 50,
    "nature": "ずぶとい",
    "ability": "おうごんのからだ",
    "item": "たべのこし",
    "Ttype": "はがね",
    "moves": [
      "サイコショック",
      "パワージェム",
      "10まんボルト",
      "ラスターカノン"
    ],
    "indiv": [
      31,
      31,
      31,
      31,
      31,
      31
    ],
    "effort": [
      252,
      0,
      252,
      0,
      16,
      0
    ]
  },
  "2": {
    "name": "ドドゲザン",
    "sex": 1,
    "level": 50,
    "nature": "れいせい",
    "ability": "まけんき",
    "item": "こだわりスカーフ",
    "Ttype": "あく",
    "moves": [
      "ストーンエッジ",
      "アイアンヘッド",
      "つるぎのまい",
      "ドゲザン"
    ],
    "indiv": [
      31,
      31,
      31,
      31,
      31,
      31
    ],
    "effort": [
      160,
      0,
      104,
      0,
      80,
      184
    ]
  },
  "3": {
    "name": "リザードン",
    "sex": -1,
    "level": 50,
    "nature": "やんちゃ",
    "ability": "サンパワー",
    "item": "いのちのたま",
    "Ttype": "ほのお",
    "moves": [
      "げきりん",
      "はねやすめ",
      "りゅうのはどう",
      "ぼうふう"
    ],
    "indiv": [
      31,
      31,
      31,
      31,
      31,
      31
    ],
    "effort": [
      120,
      112,
      144,
      0,
      0,
      152
    ]
  },
  "4": {
    "name": "ヒスイダイケンキ",
    "sex": 1,
    "level": 50,
    "nature": "しんちょう",
    "ability": "きれあじ",
    "item": "カゴのみ",
    "Ttype": "みず",
    "moves": [
      "ふいうち",
      "ひけん･ちえなみ",
      "こらえる",
      "まもる"
    ],
    "indiv": [
      31,
      31,
      31,
      31,
      31,
      31
    ],
    "effort": [
      252,
      0,
      16,
      0,
      252,
      0
    ]
  },
  "5": {
    "name": "ドリュウズ",
    "sex": -1,
    "level": 50,
    "nature": "やんちゃ",
    "ability": "すなのちから",
    "item": "ドリュウズナイト",
    "Ttype": "じめん",
    "moves": [
      "こらえる",
      "どくづき",
      "ステルスロック",
      "つるぎのまい"
    ],
    "indiv": [
      31,
      31,
      31,
      31,
      31,
      31
    ],
    "effort": [
      252,
      252,
      0,
      0,
      0,
      16
    ]
  }
}