{
  "0": {
    "name": "ミロカロス",
    "sex": 1,
    "level": 50,
    "nature": "わんぱく",
    "ability": "ふしぎなうろこ",
    "item": "こだわりスカーフ",
    "Ttype": "みず",
    "moves": [
      "とぐろをまく",
      "なみのり",
      "くろいきり",
      "ドラゴンテール"
    ],
    "indiv": [
      31,
      31,
      31,
      31,
      31,
      31
    ],
    "effort": [
      252,
      0,
      0,
      0,
      16,
      252
    ],
    "ev_category": "max_out"
  },
  "1": {
    "name": "ブリジュラス",
    "sex": -1,
    "level": 50,
    "nature": "さみしがり",
    "ability": "すじがねいり",
    "item": "オボンのみ",
    "Ttype": "はがね",
    "moves": [
      "ドラゴンテール",
      "バークアウト",
      "がんせきふうじ",
      "10まんボルト"
    ],
    "indiv": [
      31,
      31,
      31,
      31,
      31,
      31
    ],
    "effort": [
      16,
      252,
      0,
      0,
      0,
      252
    ],
    "ev_category": "max_out"
  },
  "2": {
    "name": "ヤバソチャ",
    "sex": 1,
    "level": 50,
    "nature": "ひかえめ",
    "ability": "たいねつ",
    "item": "カゴのみ",
    "Ttype": "くさ",
    "moves": [
      "たたりめ",
      "シャカシャカほう",
      "まもる",
      "おきみやげ"
    ],
    "indiv": [
      31,
      31,
      31,
      31,
      31,
      31
    ],
    "effort": [
      252,
      0,
      252,
      0,
      16,
      0
    ],
    "ev_category": "max_out"
  },
  "3": {
    "name": "ドラミドロ",
    "sex": -1,
    "level": 50,
    "nature": "いじっぱり",
    "ability": "てきおうりょく",
    "item": "フォーカスレンズ",
    "Ttype": "どく",
    "moves": [
      "ヘドロウェーブ",
      "なみのり",
      "まもる",
      "どくどく"
    ],
    "indiv": [
      31,
      31,
      31,
      31,
      31,
      31
    ],
    "effort": [
      216,
      0,
      0,
      0,
      136,
      176
    ],
    "ev_category": "hybrid"
  },
  "4": {
    "name": "エルフーン",
    "sex": 1,
    "level": 50,
    "nature": "れいせい",
    "ability": "すりぬけ",
    "item": "メトロノーム",
    "Ttype": "くさ",
    "moves": [
      "しびれごな",
      "ちょうはつ",
      "おいかぜ",
      "まもる"
    ],
    "indiv": [
      31,
      31,
      31,
      31,
      31,
      31
    ],
    "effort": [
      176,
      144,
      208,
      0,
      0,
      0
    ],
    "ev_category": "hybrid"
  },
  "5": {
    "name": "フシギバナ",
    "sex": -1,
    "level": 50,
    "nature": "ようき",
    "ability": "しんりょく",
    "item": "いのちのたま",
    "Ttype": "くさ",
    "moves": [
      "ギガドレイン",
      "アシッドボム",
      "こうごうせい",
      "まもる"
    ],
    "indiv": [
      31,
      31,
      31,
      31,
      31,
      31
    ],
    "effort": [
      252,
      252,
      0,
      0,
      0,
      16
    ],
    "ev_category": "max_out"
  }
}