{
  "0": {
    "name": "アシレーヌ",
    "sex": 1,
    "level": 50,
    "nature": "ずぶとい",
    "ability": "うるおいボイス",
    "item": "ピントレンズ",
    "Ttype": "みず",
    "moves": [
      "うたかたのアリア",
      "ムーンフォース",
      "なみのり",
      "シャドーボール"
    ],
    "indiv": [
      31,
      31,
      31,
      31,
      31,
      31
    ],
    "effort": [
      88,
      96,
      72,
      76,
      88,
      88
    ]
  },
  "1": {
    "name": "サーフゴー",
    "sex": -1,
    "level": 50,
    "nature": "ずぶとい",
    "ability": "おうごんのからだ",
    "item": "たべのこし",
    "Ttype": "はがね",
    "moves": [
      "ラスターカノン",
      "10まんボルト",
      "ゴールドラッシュ",
      "シャドーボール"
    ],
    "indiv": [
      31,
      31,
      31,
      31,
      31,
      31
    ],
    "effort": [
      72,
      80,
      72,
      80,
      88,
      116
    ]
  },
  "2": {
    "name": "サザンドラ",
    "sex": 1,
    "level": 50,
    "nature": "ひかえめ",
    "ability": "ふゆう",
    "item": "たつじんのおび",
    "Ttype": "あく",
    "moves": [
      "きあいだま",
      "だいちのちから",
      "あくのはどう",
      "だいもんじ"
    ],
    "indiv": [
      31,
      31,
      31,
      31,
      31,
      31
    ],
    "effort": [
      104,
      88,
      76,
      64,
      80,
      96
    ]
  },
  "3": {
    "name": "アーマーガア",
    "sex": -1,
    "level": 50,
    "nature": "わんぱく",
    "ability": "プレッシャー",
    "item": "しんぴのしずく",
    "Ttype": "ひこう",
    "moves": [
      "とんぼがえり",
      "ボディプレス",
      "みがわり",
      "きりばらい"
    ],
    "indiv": [
      31,
      31,
      31,
      31,
      31,
      31
    ],
    "effort": [
      252,
      0,
      4,
      252,
      0,
      0
    ]
  },
  "4": {
    "name": "ドラパルト",
    "sex": 1,
    "level": 50,
    "nature": "ようき",
    "ability": "クリアボディ",
    "item": "こだわりスカーフ",
    "Ttype": "ドラゴン",
    "moves": [
      "まもる",
      "シャドーボール",
      "りゅうせいぐん",
      "ゴーストダイブ"
    ],
    "indiv": [
      31,
      31,
      31,
      31,
      31,
      31
    ],
    "effort": [
      0,
      0,
      252,
      0,
      252,
      4
    ]
  },
  "5": {
    "name": "ドドゲザン",
    "sex": -1,
    "level": 50,
    "nature": "いじっぱり",
    "ability": "プレッシャー",
    "item": "オレンのみ",
    "Ttype": "あく",
    "moves": [
      "ドゲザン",
      "かわらわり",
      "ステルスロック",
      "けたぐり"
    ],
    "indiv": [
      31,
      31,
      31,
      31,
      31,
      31
    ],
    "effort": [
      252,
      0,
      0,
      0,
      252,
      4
    ]
  }
}